README.md
setup.py
stylelens_object/__init__.py
stylelens_object/database.py
stylelens_object/database_feature.py
stylelens_object/features.py
stylelens_object/objects.py
stylelens_object.egg-info/PKG-INFO
stylelens_object.egg-info/SOURCES.txt
stylelens_object.egg-info/dependency_links.txt
stylelens_object.egg-info/requires.txt
stylelens_object.egg-info/top_level.txt