Metadata-Version: 1.0
Name: stylelens-object
Version: 0.0.39
Summary: stylelens-object
Home-page: UNKNOWN
Author: UNKNOWN
Author-email: master@bluehack.net
License: UNKNOWN
Keywords: Swagger,stylelens-object
Platform: UNKNOWN
